pydialogflow_fulfillment/__init__.py
pydialogflow_fulfillment/default.py
pydialogflow_fulfillment/dialogflow_request.py
pydialogflow_fulfillment/dialogflow_response.py
pydialogflow_fulfillment/response.py
pydialogflow_fulfillment/telegram_response.py
pydialogflow_fulfillment-0.1.4.dist-info/LICENSE
pydialogflow_fulfillment-0.1.4.dist-info/METADATA
pydialogflow_fulfillment-0.1.4.dist-info/WHEEL
pydialogflow_fulfillment-0.1.4.dist-info/top_level.txt
pydialogflow_fulfillment-0.1.4.dist-info/RECORD
