Metadata-Version: 2.1
Name: pydialogflow-fulfillment
Version: 0.1.4
Summary: This Library makes creating fulfillment for Dialogflow v2 agents with Django or Flask easy and simple
Home-page: https://github.com/Emmarex/dialogflow-fulfillment-python
Author: Tairu Oluwafemi Emmanuel
Author-email: developer.emmarex@gmail.com
License: UNKNOWN
Download-URL: https://github.com/Emmarex/dialogflow-fulfillment-python/archive/0.1.4.tar.gz
Keywords: Dialogflow,Dialogflow fulfillment,Dialogflow fulfillment v2,pydialogflow_fulfillment
Platform: UNKNOWN
Classifier: Programming Language :: Python :: 3.6
Classifier: Programming Language :: Python :: 3.7
Classifier: Programming Language :: Python :: 3.8
Classifier: License :: OSI Approved :: Apache Software License
Classifier: Development Status :: 6 - Mature
Classifier: Intended Audience :: Developers
Classifier: Framework :: Django
Classifier: Framework :: Flask
